LICENSE
MANIFEST.in
README.md
pyproject.toml
setup.py
src/clusterondemandoci/__init__.py
src/clusterondemandoci/base.py
src/clusterondemandoci/brightsetup.py
src/clusterondemandoci/cli.py
src/clusterondemandoci/client.py
src/clusterondemandoci/client_base.py
src/clusterondemandoci/cluster.py
src/clusterondemandoci/clustercreate.py
src/clusterondemandoci/clusterdelete.py
src/clusterondemandoci/clusterlist.py
src/clusterondemandoci/clusterstart.py
src/clusterondemandoci/clusterstop.py
src/clusterondemandoci/configdump.py
src/clusterondemandoci/configshow.py
src/clusterondemandoci/configuration.py
src/clusterondemandoci/const.py
src/clusterondemandoci/imagelist.py
src/clusterondemandoci/images.py
src/clusterondemandoci/summary.py
src/clusterondemandoci/utils.py
src/clusterondemandoci/oci_actions/__init__.py
src/clusterondemandoci/oci_actions/blockstorage.py
src/clusterondemandoci/oci_actions/compute.py
src/clusterondemandoci/oci_actions/filestorage.py
src/clusterondemandoci/oci_actions/identity.py
src/clusterondemandoci/oci_actions/marketplace.py
src/clusterondemandoci/oci_actions/search.py
src/clusterondemandoci/oci_actions/virtual_network.py
src/clusterondemandoci/oci_actions/workrequest.py
src/cm_cluster_on_demand_oci.egg-info/PKG-INFO
src/cm_cluster_on_demand_oci.egg-info/SOURCES.txt
src/cm_cluster_on_demand_oci.egg-info/dependency_links.txt
src/cm_cluster_on_demand_oci.egg-info/entry_points.txt
src/cm_cluster_on_demand_oci.egg-info/requires.txt
src/cm_cluster_on_demand_oci.egg-info/top_level.txt