Metadata-Version: 2.4
Name: cm-cluster-on-demand-oci
Version: 11.0.5
Summary: NVIDIA Base Command Manager Cluster on Demand OCI
Author-email: Base Command Manager Cloud Team <sw-bright-cloud-team@nvidia.onmicrosoft.com>
License-Expression: Apache-2.0
Project-URL: Documentation, https://docs.nvidia.com/base-command-manager/
Classifier: Development Status :: 5 - Production/Stable
Classifier: Intended Audience :: Information Technology
Classifier: Intended Audience :: Science/Research
Classifier: Intended Audience :: System Administrators
Classifier: Programming Language :: Python :: 3 :: Only
Classifier: Programming Language :: Python :: 3.12
Classifier: Topic :: System :: Clustering
Classifier: Topic :: System :: Installation/Setup
Classifier: Topic :: System :: Monitoring
Classifier: Topic :: System :: Systems Administration
Requires-Python: >=3.12
License-File: LICENSE
Requires-Dist: cm-cluster-on-demand==11.0.5
Requires-Dist: cm-cluster-on-demand-config==11.0.5
Requires-Dist: oci>=2.118.2
Dynamic: license-file
Dynamic: requires-dist
